LICENSE
README.md
pyproject.toml
chkbit/__init__.py
chkbit/context.py
chkbit/hashfile.py
chkbit/ignore.py
chkbit/index.py
chkbit/index_thread.py
chkbit/input_item.py
chkbit/status.py
chkbit.egg-info/PKG-INFO
chkbit.egg-info/SOURCES.txt
chkbit.egg-info/dependency_links.txt
chkbit.egg-info/entry_points.txt
chkbit.egg-info/requires.txt
chkbit.egg-info/top_level.txt
chkbit_cli/__init__.py
chkbit_cli/cli.py
chkbit_cli/main.py
chkbit_cli/progress.py
chkbit_cli/rate_calc.py
chkbit_cli/sparklines.py