Metadata-Version: 2.1
Name: chkbit
Version: 4.0.0
Summary: chkbit checks the data integrity of your files
Author-email: Christian Zangl <laktak@cdak.net>
License: The MIT License (MIT)
Project-URL: Homepage, https://github.com/laktak/chkbit-py
Requires-Python: >=3.7.0
License-File: LICENSE
Requires-Dist: blake3>=0.3.4
